setup.py
tinycolor.py
tinycolor.egg-info/PKG-INFO
tinycolor.egg-info/SOURCES.txt
tinycolor.egg-info/dependency_links.txt
tinycolor.egg-info/top_level.txt