Metadata-Version: 1.0
Name: tinycolor
Version: 0.0.1
Summary: Easily print in colors using ANSI scape codes
Home-page: http://github.com/rbaron/tinycolor
Author: Raphael B.
Author-email: rbaron@rbaron.net
License: MIT
Keywords: print color terminal
Platform: UNKNOWN
